{"nm":"Bouncy Fail","ddd":0,"h":512,"w":512,"meta":{"g":"@lottiefiles/toolkit-js 0.33.2"},"layers":[{"ty":4,"nm":"X line 2","sr":1,"st":0,"op":60,"ip":26,"hd":false,"ddd":0,"bm":0,"hasMask":false,"ao":0,"ks":{"a":{"a":0,"k":[41,-3,0],"ix":1},"s":{"a":0,"k":[100,100,100],"ix":6},"sk":{"a":0,"k":0},"p":{"a":0,"k":[256,256,0],"ix":2},"r":{"a":0,"k":90,"ix":10},"sa":{"a":0,"k":0},"o":{"a":0,"k":100,"ix":11}},"ef":[],"shapes":[{"ty":"gr","bm":0,"hd":false,"mn":"ADBE Vector Group","nm":"Shape 1","ix":1,"cix":2,"np":3,"it":[{"ty":"sh","bm":0,"hd":false,"mn":"ADBE Vector Shape - Group","nm":"Path 1","ix":1,"d":1,"ks":{"a":0,"k":{"c":false,"i":[[0,0],[0,0]],"o":[[0,0],[0,0]],"v":[[112,-74],[-30,68]]},"ix":2}},{"ty":"st","bm":0,"hd":false,"mn":"ADBE Vector Graphic - Stroke","nm":"Stroke 1","lc":2,"lj":2,"ml":1,"o":{"a":0,"k":100,"ix":4},"w":{"a":0,"k":40,"ix":5},"c":{"a":0,"k":[0.9412,0.9373,0.9608],"ix":3}},{"ty":"fl","bm":0,"hd":false,"mn":"ADBE Vector Graphic - Fill","nm":"Fill 1","c":{"a":0,"k":[0.1725,0.2784,0.4431],"ix":4},"r":1,"o":{"a":0,"k":100,"ix":5}},{"ty":"tr","a":{"a":0,"k":[0,0],"ix":1},"s":{"a":0,"k":[100,100],"ix":3},"sk":{"a":0,"k":0,"ix":4},"p":{"a":0,"k":[0,0],"ix":2},"r":{"a":0,"k":0,"ix":6},"sa":{"a":0,"k":0,"ix":5},"o":{"a":0,"k":100,"ix":7}}]},{"ty":"tm","bm":0,"hd":false,"mn":"ADBE Vector Filter - Trim","nm":"Trim Paths 1","ix":2,"e":{"a":0,"k":100,"ix":2},"o":{"a":0,"k":0,"ix":3},"s":{"a":1,"k":[{"o":{"x":0.333,"y":0},"i":{"x":0.667,"y":1},"s":[100],"t":26},{"s":[0],"t":40}],"ix":1},"m":1}],"ind":1},{"ty":4,"nm":"X line 1","sr":1,"st":0,"op":60,"ip":26,"hd":false,"ddd":0,"bm":0,"hasMask":false,"ao":0,"ks":{"a":{"a":0,"k":[41,-3,0],"ix":1},"s":{"a":0,"k":[100,100,100],"ix":6},"sk":{"a":0,"k":0},"p":{"a":0,"k":[256,256,0],"ix":2},"r":{"a":0,"k":0,"ix":10},"sa":{"a":0,"k":0},"o":{"a":0,"k":100,"ix":11}},"ef":[],"shapes":[{"ty":"gr","bm":0,"hd":false,"mn":"ADBE Vector Group","nm":"Shape 1","ix":1,"cix":2,"np":3,"it":[{"ty":"sh","bm":0,"hd":false,"mn":"ADBE Vector Shape - Group","nm":"Path 1","ix":1,"d":1,"ks":{"a":0,"k":{"c":false,"i":[[0,0],[0,0]],"o":[[0,0],[0,0]],"v":[[112,-74],[-30,68]]},"ix":2}},{"ty":"st","bm":0,"hd":false,"mn":"ADBE Vector Graphic - Stroke","nm":"Stroke 1","lc":2,"lj":2,"ml":1,"o":{"a":0,"k":100,"ix":4},"w":{"a":0,"k":40,"ix":5},"c":{"a":0,"k":[0.9412,0.9373,0.9608],"ix":3}},{"ty":"fl","bm":0,"hd":false,"mn":"ADBE Vector Graphic - Fill","nm":"Fill 1","c":{"a":0,"k":[0.1725,0.2784,0.4431],"ix":4},"r":1,"o":{"a":0,"k":100,"ix":5}},{"ty":"tr","a":{"a":0,"k":[0,0],"ix":1},"s":{"a":0,"k":[100,100],"ix":3},"sk":{"a":0,"k":0,"ix":4},"p":{"a":0,"k":[0,0],"ix":2},"r":{"a":0,"k":0,"ix":6},"sa":{"a":0,"k":0,"ix":5},"o":{"a":0,"k":100,"ix":7}}]},{"ty":"tm","bm":0,"hd":false,"mn":"ADBE Vector Filter - Trim","nm":"Trim Paths 1","ix":2,"e":{"a":1,"k":[{"o":{"x":0.333,"y":0},"i":{"x":0.667,"y":1},"s":[0],"t":26},{"s":[100],"t":40}],"ix":2},"o":{"a":0,"k":0,"ix":3},"s":{"a":0,"k":0,"ix":1},"m":1}],"ind":2},{"ty":4,"nm":"Circle 2","sr":1,"st":0,"op":360,"ip":10,"hd":false,"ddd":0,"bm":0,"hasMask":false,"ao":0,"ks":{"a":{"a":0,"k":[140.061,140.061,0],"ix":1},"s":{"a":1,"k":[{"o":{"x":0.167,"y":0.167},"i":{"x":0.667,"y":1},"s":[0,0,100],"t":10},{"s":[140,140,100],"t":20}],"ix":6,"x":"var $bm_rt;\nvar scaleInertialBounce, scaleBounceBack, n, n, t, t, v, amp, freq, decay, v, amp, freq, decay, e, g, nMax, e, g, nMax, n, n, t, v, vl, vu, vu, tCur, segDur, tNext, nb, delta;\nscaleInertialBounce = effect('Bounce & Drop - ukramedia.com')(16);\nscaleBounceBack = effect('Bounce & Drop - ukramedia.com')(17);\ntry {\n    if (scaleInertialBounce == 1) {\n        $bm_rt = n = 0;\n        if (numKeys > 0) {\n            $bm_rt = n = nearestKey(time).index;\n            if (key(n).time > time) {\n                n--;\n            }\n        }\n        if (n == 0) {\n            $bm_rt = t = 0;\n        } else {\n            $bm_rt = t = $bm_sub(time, key(n).time);\n        }\n        if (effect('Bounce & Drop - ukramedia.com')(58) == 1) {\n            if (n > 0 && t < 1) {\n                v = velocityAtTime($bm_sub(key(n).time, $bm_div(thisComp.frameDuration, 10)));\n                amp = effect('Bounce & Drop - ukramedia.com')(59);\n                freq = effect('Bounce & Drop - ukramedia.com')(60);\n                decay = effect('Bounce & Drop - ukramedia.com')(61);\n                $bm_rt = $bm_sum(value, $bm_div($bm_mul($bm_mul(v, amp), Math.sin($bm_mul($bm_mul($bm_mul(freq, t), 2), Math.PI))), Math.exp($bm_mul(decay, t))));\n            } else {\n                $bm_rt = value;\n            }\n        } else {\n            if (n > 0 && t < 1) {\n                v = velocityAtTime($bm_sub(key(n).time, $bm_div(thisComp.frameDuration, 10)));\n                amp = effect('Bounce & Drop - ukramedia.com')(19);\n                freq = effect('Bounce & Drop - ukramedia.com')(20);\n                decay = effect('Bounce & Drop - ukramedia.com')(21);\n                $bm_rt = $bm_sum(value, $bm_div($bm_mul($bm_mul(v, amp), Math.sin($bm_mul($bm_mul($bm_mul(freq, t), 2), Math.PI))), Math.exp($bm_mul(decay, t))));\n            } else {\n                $bm_rt = value;\n            }\n        }\n    } else if (scaleBounceBack == 1) {\n        if (effect('Bounce & Drop - ukramedia.com')(64) == 1) {\n            e = effect('Bounce & Drop - ukramedia.com')(65);\n            g = effect('Bounce & Drop - ukramedia.com')(66);\n            nMax = effect('Bounce & Drop - ukramedia.com')(67);\n        } else {\n            e = effect('Bounce & Drop - ukramedia.com')(24);\n            g = effect('Bounce & Drop - ukramedia.com')(25);\n            nMax = effect('Bounce & Drop - ukramedia.com')(26);\n        }\n        $bm_rt = n = 0;\n        if (numKeys > 0) {\n            $bm_rt = n = nearestKey(time).index;\n            if (key(n).time > time)\n                n--;\n        }\n        if (n > 0) {\n            t = $bm_sub(time, key(n).time);\n            v = $bm_mul($bm_neg(velocityAtTime($bm_sub(key(n).time, 0.001))), e);\n            vl = length(v);\n            if ($bm_isInstanceOfArray(value)) {\n                vu = vl > 0 ? normalize(v) : [\n                    0,\n                    0,\n                    0\n                ];\n            } else {\n                vu = v < 0 ? -1 : 1;\n            }\n            tCur = 0;\n            segDur = $bm_div($bm_mul(2, vl), g);\n            tNext = segDur;\n            nb = 1;\n            while (tNext < t && nb <= nMax) {\n                vl *= e;\n                segDur *= e;\n                tCur = tNext;\n                tNext = $bm_sum(tNext, segDur);\n                nb++;\n            }\n            if (nb <= nMax) {\n                delta = $bm_sub(t, tCur);\n                $bm_rt = $bm_sum(value, $bm_mul($bm_mul(vu, delta), $bm_sub(vl, $bm_div($bm_mul(g, delta), 2))));\n            } else {\n                $bm_rt = value;\n            }\n        } else\n            $bm_rt = value;\n    } else {\n        $bm_rt = value;\n    }\n} catch (err) {\n    $bm_rt = value;\n}"},"sk":{"a":0,"k":0},"p":{"a":0,"k":[256,256,0],"ix":2,"x":"var $bm_rt;\nvar positionInertialBounce, positionBounceBack, n, n, t, t, v, amp, freq, decay, v, amp, freq, decay, e, g, nMax, e, g, nMax, n, n, t, v, vl, vu, vu, tCur, segDur, tNext, nb, delta;\npositionInertialBounce = effect('Bounce & Drop - ukramedia.com')(2);\npositionBounceBack = effect('Bounce & Drop - ukramedia.com')(3);\ntry {\n    if (positionInertialBounce == 1) {\n        $bm_rt = n = 0;\n        if (numKeys > 0) {\n            $bm_rt = n = nearestKey(time).index;\n            if (key(n).time > time) {\n                n--;\n            }\n        }\n        if (n == 0) {\n            $bm_rt = t = 0;\n        } else {\n            $bm_rt = t = $bm_sub(time, key(n).time);\n        }\n        if (effect('Bounce & Drop - ukramedia.com')(58) == 1) {\n            if (n > 0 && t < 1) {\n                v = velocityAtTime($bm_sub(key(n).time, $bm_div(thisComp.frameDuration, 10)));\n                amp = effect('Bounce & Drop - ukramedia.com')(59);\n                freq = effect('Bounce & Drop - ukramedia.com')(60);\n                decay = effect('Bounce & Drop - ukramedia.com')(61);\n                $bm_rt = $bm_sum(value, $bm_div($bm_mul($bm_mul(v, amp), Math.sin($bm_mul($bm_mul($bm_mul(freq, t), 2), Math.PI))), Math.exp($bm_mul(decay, t))));\n            } else {\n                $bm_rt = value;\n            }\n        } else {\n            if (n > 0 && t < 1) {\n                v = velocityAtTime($bm_sub(key(n).time, $bm_div(thisComp.frameDuration, 10)));\n                amp = effect('Bounce & Drop - ukramedia.com')(5);\n                freq = effect('Bounce & Drop - ukramedia.com')(6);\n                decay = effect('Bounce & Drop - ukramedia.com')(7);\n                $bm_rt = $bm_sum(value, $bm_div($bm_mul($bm_mul(v, amp), Math.sin($bm_mul($bm_mul($bm_mul(freq, t), 2), Math.PI))), Math.exp($bm_mul(decay, t))));\n            } else {\n                $bm_rt = value;\n            }\n        }\n    } else if (positionBounceBack == 1) {\n        if (effect('Bounce & Drop - ukramedia.com')(64) == 1) {\n            e = effect('Bounce & Drop - ukramedia.com')(65);\n            g = effect('Bounce & Drop - ukramedia.com')(66);\n            nMax = effect('Bounce & Drop - ukramedia.com')(67);\n        } else {\n            e = effect('Bounce & Drop - ukramedia.com')(10);\n            g = effect('Bounce & Drop - ukramedia.com')(11);\n            nMax = effect('Bounce & Drop - ukramedia.com')(12);\n        }\n        $bm_rt = n = 0;\n        if (numKeys > 0) {\n            $bm_rt = n = nearestKey(time).index;\n            if (key(n).time > time)\n                n--;\n        }\n        if (n > 0) {\n            t = $bm_sub(time, key(n).time);\n            v = $bm_mul($bm_neg(velocityAtTime($bm_sub(key(n).time, 0.001))), e);\n            vl = length(v);\n            if ($bm_isInstanceOfArray(value)) {\n                vu = vl > 0 ? normalize(v) : [\n                    0,\n                    0,\n                    0\n                ];\n            } else {\n                vu = v < 0 ? -1 : 1;\n            }\n            tCur = 0;\n            segDur = $bm_div($bm_mul(2, vl), g);\n            tNext = segDur;\n            nb = 1;\n            while (tNext < t && nb <= nMax) {\n                vl *= e;\n                segDur *= e;\n                tCur = tNext;\n                tNext = $bm_sum(tNext, segDur);\n                nb++;\n            }\n            if (nb <= nMax) {\n                delta = $bm_sub(t, tCur);\n                $bm_rt = $bm_sum(value, $bm_mul($bm_mul(vu, delta), $bm_sub(vl, $bm_div($bm_mul(g, delta), 2))));\n            } else {\n                $bm_rt = value;\n            }\n        } else\n            $bm_rt = value;\n    } else {\n        $bm_rt = value;\n    }\n} catch (err) {\n    $bm_rt = value;\n}"},"r":{"a":0,"k":0,"ix":10,"x":"var $bm_rt;\nvar rotationInertialBounce, rotationBounceBack, n, n, t, t, v, amp, freq, decay, v, amp, freq, decay, e, g, nMax, e, g, nMax, n, n, t, v, vl, vu, vu, tCur, segDur, tNext, nb, delta;\nrotationInertialBounce = effect('Bounce & Drop - ukramedia.com')(30);\nrotationBounceBack = effect('Bounce & Drop - ukramedia.com')(31);\ntry {\n    if (rotationInertialBounce == 1) {\n        $bm_rt = n = 0;\n        if (numKeys > 0) {\n            $bm_rt = n = nearestKey(time).index;\n            if (key(n).time > time) {\n                n--;\n            }\n        }\n        if (n == 0) {\n            $bm_rt = t = 0;\n        } else {\n            $bm_rt = t = $bm_sub(time, key(n).time);\n        }\n        if (effect('Bounce & Drop - ukramedia.com')(58) == 1) {\n            if (n > 0 && t < 1) {\n                v = velocityAtTime($bm_sub(key(n).time, $bm_div(thisComp.frameDuration, 10)));\n                amp = effect('Bounce & Drop - ukramedia.com')(59);\n                freq = effect('Bounce & Drop - ukramedia.com')(60);\n                decay = effect('Bounce & Drop - ukramedia.com')(61);\n                $bm_rt = $bm_sum(value, $bm_div($bm_mul($bm_mul(v, amp), Math.sin($bm_mul($bm_mul($bm_mul(freq, t), 2), Math.PI))), Math.exp($bm_mul(decay, t))));\n            } else {\n                $bm_rt = value;\n            }\n        } else {\n            if (n > 0 && t < 1) {\n                v = velocityAtTime($bm_sub(key(n).time, $bm_div(thisComp.frameDuration, 10)));\n                amp = effect('Bounce & Drop - ukramedia.com')(33);\n                freq = effect('Bounce & Drop - ukramedia.com')(34);\n                decay = effect('Bounce & Drop - ukramedia.com')(35);\n                $bm_rt = $bm_sum(value, $bm_div($bm_mul($bm_mul(v, amp), Math.sin($bm_mul($bm_mul($bm_mul(freq, t), 2), Math.PI))), Math.exp($bm_mul(decay, t))));\n            } else {\n                $bm_rt = value;\n            }\n        }\n    } else if (rotationBounceBack == 1) {\n        if (effect('Bounce & Drop - ukramedia.com')(64) == 1) {\n            e = effect('Bounce & Drop - ukramedia.com')(65);\n            g = effect('Bounce & Drop - ukramedia.com')(66);\n            nMax = effect('Bounce & Drop - ukramedia.com')(67);\n        } else {\n            e = effect('Bounce & Drop - ukramedia.com')(38);\n            g = effect('Bounce & Drop - ukramedia.com')(39);\n            nMax = effect('Bounce & Drop - ukramedia.com')(40);\n        }\n        $bm_rt = n = 0;\n        if (numKeys > 0) {\n            $bm_rt = n = nearestKey(time).index;\n            if (key(n).time > time)\n                n--;\n        }\n        if (n > 0) {\n            t = $bm_sub(time, key(n).time);\n            v = $bm_mul($bm_neg(velocityAtTime($bm_sub(key(n).time, 0.001))), e);\n            vl = length(v);\n            if ($bm_isInstanceOfArray(value)) {\n                vu = vl > 0 ? normalize(v) : [\n                    0,\n                    0,\n                    0\n                ];\n            } else {\n                vu = v < 0 ? -1 : 1;\n            }\n            tCur = 0;\n            segDur = $bm_div($bm_mul(2, vl), g);\n            tNext = segDur;\n            nb = 1;\n            while (tNext < t && nb <= nMax) {\n                vl *= e;\n                segDur *= e;\n                tCur = tNext;\n                tNext = $bm_sum(tNext, segDur);\n                nb++;\n            }\n            if (nb <= nMax) {\n                delta = $bm_sub(t, tCur);\n                $bm_rt = $bm_sum(value, $bm_mul($bm_mul(vu, delta), $bm_sub(vl, $bm_div($bm_mul(g, delta), 2))));\n            } else {\n                $bm_rt = value;\n            }\n        } else\n            $bm_rt = value;\n    } else {\n        $bm_rt = value;\n    }\n} catch (err) {\n    $bm_rt = value;\n}"},"sa":{"a":0,"k":0},"o":{"a":0,"k":100,"ix":11,"x":"var $bm_rt;\nvar opacityInertialBounce, opacityBounceBack, n, n, t, t, v, amp, freq, decay, v, amp, freq, decay, e, g, nMax, e, g, nMax, n, n, t, v, vl, vu, vu, tCur, segDur, tNext, nb, delta;\nopacityInertialBounce = effect('Bounce & Drop - ukramedia.com')(44);\nopacityBounceBack = effect('Bounce & Drop - ukramedia.com')(45);\ntry {\n    if (opacityInertialBounce == 1) {\n        $bm_rt = n = 0;\n        if (numKeys > 0) {\n            $bm_rt = n = nearestKey(time).index;\n            if (key(n).time > time) {\n                n--;\n            }\n        }\n        if (n == 0) {\n            $bm_rt = t = 0;\n        } else {\n            $bm_rt = t = $bm_sub(time, key(n).time);\n        }\n        if (effect('Bounce & Drop - ukramedia.com')(58) == 1) {\n            if (n > 0 && t < 1) {\n                v = velocityAtTime($bm_sub(key(n).time, $bm_div(thisComp.frameDuration, 10)));\n                amp = effect('Bounce & Drop - ukramedia.com')(59);\n                freq = effect('Bounce & Drop - ukramedia.com')(60);\n                decay = effect('Bounce & Drop - ukramedia.com')(61);\n                $bm_rt = $bm_sum(value, $bm_div($bm_mul($bm_mul(v, amp), Math.sin($bm_mul($bm_mul($bm_mul(freq, t), 2), Math.PI))), Math.exp($bm_mul(decay, t))));\n            } else {\n                $bm_rt = value;\n            }\n        } else {\n            if (n > 0 && t < 1) {\n                v = velocityAtTime($bm_sub(key(n).time, $bm_div(thisComp.frameDuration, 10)));\n                amp = effect('Bounce & Drop - ukramedia.com')(47);\n                freq = effect('Bounce & Drop - ukramedia.com')(48);\n                decay = effect('Bounce & Drop - ukramedia.com')(49);\n                $bm_rt = $bm_sum(value, $bm_div($bm_mul($bm_mul(v, amp), Math.sin($bm_mul($bm_mul($bm_mul(freq, t), 2), Math.PI))), Math.exp($bm_mul(decay, t))));\n            } else {\n                $bm_rt = value;\n            }\n        }\n    } else if (opacityBounceBack == 1) {\n        if (effect('Bounce & Drop - ukramedia.com')(64) == 1) {\n            e = effect('Bounce & Drop - ukramedia.com')(65);\n            g = effect('Bounce & Drop - ukramedia.com')(66);\n            nMax = effect('Bounce & Drop - ukramedia.com')(67);\n        } else {\n            e = effect('Bounce & Drop - ukramedia.com')(52);\n            g = effect('Bounce & Drop - ukramedia.com')(53);\n            nMax = effect('Bounce & Drop - ukramedia.com')(54);\n        }\n        $bm_rt = n = 0;\n        if (numKeys > 0) {\n            $bm_rt = n = nearestKey(time).index;\n            if (key(n).time > time)\n                n--;\n        }\n        if (n > 0) {\n            t = $bm_sub(time, key(n).time);\n            v = $bm_mul($bm_neg(velocityAtTime($bm_sub(key(n).time, 0.001))), e);\n            vl = length(v);\n            if ($bm_isInstanceOfArray(value)) {\n                vu = vl > 0 ? normalize(v) : [\n                    0,\n                    0,\n                    0\n                ];\n            } else {\n                vu = v < 0 ? -1 : 1;\n            }\n            tCur = 0;\n            segDur = $bm_div($bm_mul(2, vl), g);\n            tNext = segDur;\n            nb = 1;\n            while (tNext < t && nb <= nMax) {\n                vl *= e;\n                segDur *= e;\n                tCur = tNext;\n                tNext = $bm_sum(tNext, segDur);\n                nb++;\n            }\n            if (nb <= nMax) {\n                delta = $bm_sub(t, tCur);\n                $bm_rt = $bm_sum(value, $bm_mul($bm_mul(vu, delta), $bm_sub(vl, $bm_div($bm_mul(g, delta), 2))));\n            } else {\n                $bm_rt = value;\n            }\n        } else\n            $bm_rt = value;\n    } else {\n        $bm_rt = value;\n    }\n} catch (err) {\n    $bm_rt = value;\n}"}},"ef":[{"ty":5,"mn":"Pseudo/animationControl","nm":"Bounce & Drop - ukramedia.com","ix":1,"en":1,"ef":[{"ty":6,"mn":"Pseudo/animationControl-0001","nm":"Position","ix":1,"v":0},{"ty":7,"mn":"Pseudo/animationControl-0002","nm":"Enable Inertial Bounce","ix":2,"v":{"a":0,"k":0,"ix":2}},{"ty":7,"mn":"Pseudo/animationControl-0003","nm":"Enable Bounce Back","ix":3,"v":{"a":0,"k":0,"ix":3}},{"ty":6,"mn":"Pseudo/animationControl-0004","nm":"Inertial Bounce Options","ix":4,"v":0},{"ty":0,"mn":"Pseudo/animationControl-0005","nm":"Amplitude","ix":5,"v":{"a":0,"k":0.05,"ix":5}},{"ty":0,"mn":"Pseudo/animationControl-0006","nm":"Frequency","ix":6,"v":{"a":0,"k":4,"ix":6}},{"ty":0,"mn":"Pseudo/animationControl-0007","nm":"Decay","ix":7,"v":{"a":0,"k":8,"ix":7}},{"ty":6,"mn":"Pseudo/animationControl-0008","nm":"","ix":8,"v":0},{"ty":6,"mn":"Pseudo/animationControl-0009","nm":"Bounce Back Options","ix":9,"v":0},{"ty":0,"mn":"Pseudo/animationControl-0010","nm":"Elasticity","ix":10,"v":{"a":0,"k":0.7,"ix":10}},{"ty":0,"mn":"Pseudo/animationControl-0011","nm":"Gravity","ix":11,"v":{"a":0,"k":5000,"ix":11}},{"ty":0,"mn":"Pseudo/animationControl-0012","nm":"nMax","ix":12,"v":{"a":0,"k":9,"ix":12}},{"ty":6,"mn":"Pseudo/animationControl-0013","nm":"","ix":13,"v":0},{"ty":6,"mn":"Pseudo/animationControl-0014","nm":"","ix":14,"v":0},{"ty":6,"mn":"Pseudo/animationControl-0015","nm":"Scale","ix":15,"v":0},{"ty":7,"mn":"Pseudo/animationControl-0016","nm":"Enable Inertial Bounce","ix":16,"v":{"a":0,"k":1,"ix":16}},{"ty":7,"mn":"Pseudo/animationControl-0017","nm":"Enable Bounce Back","ix":17,"v":{"a":0,"k":0,"ix":17}},{"ty":6,"mn":"Pseudo/animationControl-0018","nm":"Inertial Bounce Options","ix":18,"v":0},{"ty":0,"mn":"Pseudo/animationControl-0019","nm":"Amplitude","ix":19,"v":{"a":0,"k":0.8,"ix":19}},{"ty":0,"mn":"Pseudo/animationControl-0020","nm":"Frequency","ix":20,"v":{"a":0,"k":4,"ix":20}},{"ty":0,"mn":"Pseudo/animationControl-0021","nm":"Decay","ix":21,"v":{"a":0,"k":8,"ix":21}},{"ty":6,"mn":"Pseudo/animationControl-0022","nm":"","ix":22,"v":0},{"ty":6,"mn":"Pseudo/animationControl-0023","nm":"Bounce Back Options","ix":23,"v":0},{"ty":0,"mn":"Pseudo/animationControl-0024","nm":"Elasticity","ix":24,"v":{"a":0,"k":0.7,"ix":24}},{"ty":0,"mn":"Pseudo/animationControl-0025","nm":"Gravity","ix":25,"v":{"a":0,"k":5000,"ix":25}},{"ty":0,"mn":"Pseudo/animationControl-0026","nm":"nMax","ix":26,"v":{"a":0,"k":9,"ix":26}},{"ty":6,"mn":"Pseudo/animationControl-0027","nm":"","ix":27,"v":0},{"ty":6,"mn":"Pseudo/animationControl-0028","nm":"","ix":28,"v":0},{"ty":6,"mn":"Pseudo/animationControl-0029","nm":"Rotation","ix":29,"v":0},{"ty":7,"mn":"Pseudo/animationControl-0030","nm":"Enable Inertial Bounce","ix":30,"v":{"a":0,"k":0,"ix":30}},{"ty":7,"mn":"Pseudo/animationControl-0031","nm":"Enable Bounce Back","ix":31,"v":{"a":0,"k":0,"ix":31}},{"ty":6,"mn":"Pseudo/animationControl-0032","nm":"Inertial Bounce Options","ix":32,"v":0},{"ty":0,"mn":"Pseudo/animationControl-0033","nm":"Amplitude","ix":33,"v":{"a":0,"k":0.05,"ix":33}},{"ty":0,"mn":"Pseudo/animationControl-0034","nm":"Frequency","ix":34,"v":{"a":0,"k":4,"ix":34}},{"ty":0,"mn":"Pseudo/animationControl-0035","nm":"Decay","ix":35,"v":{"a":0,"k":8,"ix":35}},{"ty":6,"mn":"Pseudo/animationControl-0036","nm":"","ix":36,"v":0},{"ty":6,"mn":"Pseudo/animationControl-0037","nm":"Bounce Back Options","ix":37,"v":0},{"ty":0,"mn":"Pseudo/animationControl-0038","nm":"Elasticity","ix":38,"v":{"a":0,"k":0.7,"ix":38}},{"ty":0,"mn":"Pseudo/animationControl-0039","nm":"Gravity","ix":39,"v":{"a":0,"k":5000,"ix":39}},{"ty":0,"mn":"Pseudo/animationControl-0040","nm":"nMax","ix":40,"v":{"a":0,"k":9,"ix":40}},{"ty":6,"mn":"Pseudo/animationControl-0041","nm":"","ix":41,"v":0},{"ty":6,"mn":"Pseudo/animationControl-0042","nm":"","ix":42,"v":0},{"ty":6,"mn":"Pseudo/animationControl-0043","nm":"Opacity","ix":43,"v":0},{"ty":7,"mn":"Pseudo/animationControl-0044","nm":"Enable Inertial Bounce","ix":44,"v":{"a":0,"k":0,"ix":44}},{"ty":7,"mn":"Pseudo/animationControl-0045","nm":"Enable Bounce Back","ix":45,"v":{"a":0,"k":0,"ix":45}},{"ty":6,"mn":"Pseudo/animationControl-0046","nm":"Inertial Bounce Options","ix":46,"v":0},{"ty":0,"mn":"Pseudo/animationControl-0047","nm":"Amplitude","ix":47,"v":{"a":0,"k":0.05,"ix":47}},{"ty":0,"mn":"Pseudo/animationControl-0048","nm":"Frequency","ix":48,"v":{"a":0,"k":4,"ix":48}},{"ty":0,"mn":"Pseudo/animationControl-0049","nm":"Decay","ix":49,"v":{"a":0,"k":8,"ix":49}},{"ty":6,"mn":"Pseudo/animationControl-0050","nm":"","ix":50,"v":0},{"ty":6,"mn":"Pseudo/animationControl-0051","nm":"Bounce Back Options","ix":51,"v":0},{"ty":0,"mn":"Pseudo/animationControl-0052","nm":"Elasticity","ix":52,"v":{"a":0,"k":0.7,"ix":52}},{"ty":0,"mn":"Pseudo/animationControl-0053","nm":"Gravity","ix":53,"v":{"a":0,"k":5000,"ix":53}},{"ty":0,"mn":"Pseudo/animationControl-0054","nm":"nMax","ix":54,"v":{"a":0,"k":9,"ix":54}},{"ty":6,"mn":"Pseudo/animationControl-0055","nm":"","ix":55,"v":0},{"ty":6,"mn":"Pseudo/animationControl-0056","nm":"","ix":56,"v":0},{"ty":6,"mn":"Pseudo/animationControl-0057","nm":"Global Inertial Bounce Options","ix":57,"v":0},{"ty":7,"mn":"Pseudo/animationControl-0058","nm":"Enable Global Inertial Bounce","ix":58,"v":{"a":0,"k":0,"ix":58}},{"ty":0,"mn":"Pseudo/animationControl-0059","nm":"Amplitude","ix":59,"v":{"a":0,"k":0.05,"ix":59}},{"ty":0,"mn":"Pseudo/animationControl-0060","nm":"Frequency","ix":60,"v":{"a":0,"k":4,"ix":60}},{"ty":0,"mn":"Pseudo/animationControl-0061","nm":"Decay","ix":61,"v":{"a":0,"k":8,"ix":61}},{"ty":6,"mn":"Pseudo/animationControl-0062","nm":"","ix":62,"v":0},{"ty":6,"mn":"Pseudo/animationControl-0063","nm":"Global Bounce Back Options","ix":63,"v":0},{"ty":7,"mn":"Pseudo/animationControl-0064","nm":"Enable Global Bounce Back","ix":64,"v":{"a":0,"k":0,"ix":64}},{"ty":0,"mn":"Pseudo/animationControl-0065","nm":"Elasticity","ix":65,"v":{"a":0,"k":0.7,"ix":65}},{"ty":0,"mn":"Pseudo/animationControl-0066","nm":"Gravity","ix":66,"v":{"a":0,"k":5000,"ix":66}},{"ty":0,"mn":"Pseudo/animationControl-0067","nm":"nMax","ix":67,"v":{"a":0,"k":9,"ix":67}},{"ty":6,"mn":"Pseudo/animationControl-0068","nm":"","ix":68,"v":0}]}],"shapes":[{"ty":"gr","bm":0,"hd":false,"mn":"ADBE Vector Group","nm":"Group 1","ix":1,"cix":2,"np":2,"it":[{"ty":"sh","bm":0,"hd":false,"mn":"ADBE Vector Shape - Group","nm":"Path 1","ix":1,"d":1,"ks":{"a":0,"k":{"c":true,"i":[[0,-77.215],[77.216,0],[0,77.215],[-77.215,0]],"o":[[0,77.215],[-77.215,0],[0,-77.215],[77.216,0]],"v":[[139.811,0],[0,139.811],[-139.811,0],[0,-139.811]]},"ix":2}},{"ty":"fl","bm":0,"hd":false,"mn":"ADBE Vector Graphic - Fill","nm":"Fill 1","c":{"a":0,"k":[0.1725,0.2784,0.4431],"ix":4},"r":1,"o":{"a":0,"k":100,"ix":5}},{"ty":"tr","a":{"a":0,"k":[0,0],"ix":1},"s":{"a":0,"k":[100,100],"ix":3},"sk":{"a":0,"k":0,"ix":4},"p":{"a":0,"k":[140.061,140.061],"ix":2},"r":{"a":0,"k":0,"ix":6},"sa":{"a":0,"k":0,"ix":5},"o":{"a":0,"k":100,"ix":7}}]}],"ind":3},{"ty":4,"nm":"Circle 1","sr":1,"st":0,"op":360,"ip":0,"hd":false,"ddd":0,"bm":0,"hasMask":false,"ao":0,"ks":{"a":{"a":0,"k":[140.061,140.061,0],"ix":1},"s":{"a":1,"k":[{"o":{"x":0.167,"y":0.167},"i":{"x":0.667,"y":1},"s":[0,0,100],"t":0},{"o":{"x":0.167,"y":0.167},"i":{"x":0.667,"y":1},"s":[132,132,100],"t":10},{"o":{"x":0.167,"y":0.167},"i":{"x":0.667,"y":1},"s":[130,130,100],"t":35},{"s":[175,175,100],"t":55}],"ix":6,"x":"var $bm_rt;\nvar scaleInertialBounce, scaleBounceBack, n, n, t, t, v, amp, freq, decay, v, amp, freq, decay, e, g, nMax, e, g, nMax, n, n, t, v, vl, vu, vu, tCur, segDur, tNext, nb, delta;\nscaleInertialBounce = effect('Bounce & Drop - ukramedia.com')(16);\nscaleBounceBack = effect('Bounce & Drop - ukramedia.com')(17);\ntry {\n    if (scaleInertialBounce == 1) {\n        $bm_rt = n = 0;\n        if (numKeys > 0) {\n            $bm_rt = n = nearestKey(time).index;\n            if (key(n).time > time) {\n                n--;\n            }\n        }\n        if (n == 0) {\n            $bm_rt = t = 0;\n        } else {\n            $bm_rt = t = $bm_sub(time, key(n).time);\n        }\n        if (effect('Bounce & Drop - ukramedia.com')(58) == 1) {\n            if (n > 0 && t < 1) {\n                v = velocityAtTime($bm_sub(key(n).time, $bm_div(thisComp.frameDuration, 10)));\n                amp = effect('Bounce & Drop - ukramedia.com')(59);\n                freq = effect('Bounce & Drop - ukramedia.com')(60);\n                decay = effect('Bounce & Drop - ukramedia.com')(61);\n                $bm_rt = $bm_sum(value, $bm_div($bm_mul($bm_mul(v, amp), Math.sin($bm_mul($bm_mul($bm_mul(freq, t), 2), Math.PI))), Math.exp($bm_mul(decay, t))));\n            } else {\n                $bm_rt = value;\n            }\n        } else {\n            if (n > 0 && t < 1) {\n                v = velocityAtTime($bm_sub(key(n).time, $bm_div(thisComp.frameDuration, 10)));\n                amp = effect('Bounce & Drop - ukramedia.com')(19);\n                freq = effect('Bounce & Drop - ukramedia.com')(20);\n                decay = effect('Bounce & Drop - ukramedia.com')(21);\n                $bm_rt = $bm_sum(value, $bm_div($bm_mul($bm_mul(v, amp), Math.sin($bm_mul($bm_mul($bm_mul(freq, t), 2), Math.PI))), Math.exp($bm_mul(decay, t))));\n            } else {\n                $bm_rt = value;\n            }\n        }\n    } else if (scaleBounceBack == 1) {\n        if (effect('Bounce & Drop - ukramedia.com')(64) == 1) {\n            e = effect('Bounce & Drop - ukramedia.com')(65);\n            g = effect('Bounce & Drop - ukramedia.com')(66);\n            nMax = effect('Bounce & Drop - ukramedia.com')(67);\n        } else {\n            e = effect('Bounce & Drop - ukramedia.com')(24);\n            g = effect('Bounce & Drop - ukramedia.com')(25);\n            nMax = effect('Bounce & Drop - ukramedia.com')(26);\n        }\n        $bm_rt = n = 0;\n        if (numKeys > 0) {\n            $bm_rt = n = nearestKey(time).index;\n            if (key(n).time > time)\n                n--;\n        }\n        if (n > 0) {\n            t = $bm_sub(time, key(n).time);\n            v = $bm_mul($bm_neg(velocityAtTime($bm_sub(key(n).time, 0.001))), e);\n            vl = length(v);\n            if ($bm_isInstanceOfArray(value)) {\n                vu = vl > 0 ? normalize(v) : [\n                    0,\n                    0,\n                    0\n                ];\n            } else {\n                vu = v < 0 ? -1 : 1;\n            }\n            tCur = 0;\n            segDur = $bm_div($bm_mul(2, vl), g);\n            tNext = segDur;\n            nb = 1;\n            while (tNext < t && nb <= nMax) {\n                vl *= e;\n                segDur *= e;\n                tCur = tNext;\n                tNext = $bm_sum(tNext, segDur);\n                nb++;\n            }\n            if (nb <= nMax) {\n                delta = $bm_sub(t, tCur);\n                $bm_rt = $bm_sum(value, $bm_mul($bm_mul(vu, delta), $bm_sub(vl, $bm_div($bm_mul(g, delta), 2))));\n            } else {\n                $bm_rt = value;\n            }\n        } else\n            $bm_rt = value;\n    } else {\n        $bm_rt = value;\n    }\n} catch (err) {\n    $bm_rt = value;\n}"},"sk":{"a":0,"k":0},"p":{"a":0,"k":[256,256,0],"ix":2,"x":"var $bm_rt;\nvar positionInertialBounce, positionBounceBack, n, n, t, t, v, amp, freq, decay, v, amp, freq, decay, e, g, nMax, e, g, nMax, n, n, t, v, vl, vu, vu, tCur, segDur, tNext, nb, delta;\npositionInertialBounce = effect('Bounce & Drop - ukramedia.com')(2);\npositionBounceBack = effect('Bounce & Drop - ukramedia.com')(3);\ntry {\n    if (positionInertialBounce == 1) {\n        $bm_rt = n = 0;\n        if (numKeys > 0) {\n            $bm_rt = n = nearestKey(time).index;\n            if (key(n).time > time) {\n                n--;\n            }\n        }\n        if (n == 0) {\n            $bm_rt = t = 0;\n        } else {\n            $bm_rt = t = $bm_sub(time, key(n).time);\n        }\n        if (effect('Bounce & Drop - ukramedia.com')(58) == 1) {\n            if (n > 0 && t < 1) {\n                v = velocityAtTime($bm_sub(key(n).time, $bm_div(thisComp.frameDuration, 10)));\n                amp = effect('Bounce & Drop - ukramedia.com')(59);\n                freq = effect('Bounce & Drop - ukramedia.com')(60);\n                decay = effect('Bounce & Drop - ukramedia.com')(61);\n                $bm_rt = $bm_sum(value, $bm_div($bm_mul($bm_mul(v, amp), Math.sin($bm_mul($bm_mul($bm_mul(freq, t), 2), Math.PI))), Math.exp($bm_mul(decay, t))));\n            } else {\n                $bm_rt = value;\n            }\n        } else {\n            if (n > 0 && t < 1) {\n                v = velocityAtTime($bm_sub(key(n).time, $bm_div(thisComp.frameDuration, 10)));\n                amp = effect('Bounce & Drop - ukramedia.com')(5);\n                freq = effect('Bounce & Drop - ukramedia.com')(6);\n                decay = effect('Bounce & Drop - ukramedia.com')(7);\n                $bm_rt = $bm_sum(value, $bm_div($bm_mul($bm_mul(v, amp), Math.sin($bm_mul($bm_mul($bm_mul(freq, t), 2), Math.PI))), Math.exp($bm_mul(decay, t))));\n            } else {\n                $bm_rt = value;\n            }\n        }\n    } else if (positionBounceBack == 1) {\n        if (effect('Bounce & Drop - ukramedia.com')(64) == 1) {\n            e = effect('Bounce & Drop - ukramedia.com')(65);\n            g = effect('Bounce & Drop - ukramedia.com')(66);\n            nMax = effect('Bounce & Drop - ukramedia.com')(67);\n        } else {\n            e = effect('Bounce & Drop - ukramedia.com')(10);\n            g = effect('Bounce & Drop - ukramedia.com')(11);\n            nMax = effect('Bounce & Drop - ukramedia.com')(12);\n        }\n        $bm_rt = n = 0;\n        if (numKeys > 0) {\n            $bm_rt = n = nearestKey(time).index;\n            if (key(n).time > time)\n                n--;\n        }\n        if (n > 0) {\n            t = $bm_sub(time, key(n).time);\n            v = $bm_mul($bm_neg(velocityAtTime($bm_sub(key(n).time, 0.001))), e);\n            vl = length(v);\n            if ($bm_isInstanceOfArray(value)) {\n                vu = vl > 0 ? normalize(v) : [\n                    0,\n                    0,\n                    0\n                ];\n            } else {\n                vu = v < 0 ? -1 : 1;\n            }\n            tCur = 0;\n            segDur = $bm_div($bm_mul(2, vl), g);\n            tNext = segDur;\n            nb = 1;\n            while (tNext < t && nb <= nMax) {\n                vl *= e;\n                segDur *= e;\n                tCur = tNext;\n                tNext = $bm_sum(tNext, segDur);\n                nb++;\n            }\n            if (nb <= nMax) {\n                delta = $bm_sub(t, tCur);\n                $bm_rt = $bm_sum(value, $bm_mul($bm_mul(vu, delta), $bm_sub(vl, $bm_div($bm_mul(g, delta), 2))));\n            } else {\n                $bm_rt = value;\n            }\n        } else\n            $bm_rt = value;\n    } else {\n        $bm_rt = value;\n    }\n} catch (err) {\n    $bm_rt = value;\n}"},"r":{"a":0,"k":0,"ix":10,"x":"var $bm_rt;\nvar rotationInertialBounce, rotationBounceBack, n, n, t, t, v, amp, freq, decay, v, amp, freq, decay, e, g, nMax, e, g, nMax, n, n, t, v, vl, vu, vu, tCur, segDur, tNext, nb, delta;\nrotationInertialBounce = effect('Bounce & Drop - ukramedia.com')(30);\nrotationBounceBack = effect('Bounce & Drop - ukramedia.com')(31);\ntry {\n    if (rotationInertialBounce == 1) {\n        $bm_rt = n = 0;\n        if (numKeys > 0) {\n            $bm_rt = n = nearestKey(time).index;\n            if (key(n).time > time) {\n                n--;\n            }\n        }\n        if (n == 0) {\n            $bm_rt = t = 0;\n        } else {\n            $bm_rt = t = $bm_sub(time, key(n).time);\n        }\n        if (effect('Bounce & Drop - ukramedia.com')(58) == 1) {\n            if (n > 0 && t < 1) {\n                v = velocityAtTime($bm_sub(key(n).time, $bm_div(thisComp.frameDuration, 10)));\n                amp = effect('Bounce & Drop - ukramedia.com')(59);\n                freq = effect('Bounce & Drop - ukramedia.com')(60);\n                decay = effect('Bounce & Drop - ukramedia.com')(61);\n                $bm_rt = $bm_sum(value, $bm_div($bm_mul($bm_mul(v, amp), Math.sin($bm_mul($bm_mul($bm_mul(freq, t), 2), Math.PI))), Math.exp($bm_mul(decay, t))));\n            } else {\n                $bm_rt = value;\n            }\n        } else {\n            if (n > 0 && t < 1) {\n                v = velocityAtTime($bm_sub(key(n).time, $bm_div(thisComp.frameDuration, 10)));\n                amp = effect('Bounce & Drop - ukramedia.com')(33);\n                freq = effect('Bounce & Drop - ukramedia.com')(34);\n                decay = effect('Bounce & Drop - ukramedia.com')(35);\n                $bm_rt = $bm_sum(value, $bm_div($bm_mul($bm_mul(v, amp), Math.sin($bm_mul($bm_mul($bm_mul(freq, t), 2), Math.PI))), Math.exp($bm_mul(decay, t))));\n            } else {\n                $bm_rt = value;\n            }\n        }\n    } else if (rotationBounceBack == 1) {\n        if (effect('Bounce & Drop - ukramedia.com')(64) == 1) {\n            e = effect('Bounce & Drop - ukramedia.com')(65);\n            g = effect('Bounce & Drop - ukramedia.com')(66);\n            nMax = effect('Bounce & Drop - ukramedia.com')(67);\n        } else {\n            e = effect('Bounce & Drop - ukramedia.com')(38);\n            g = effect('Bounce & Drop - ukramedia.com')(39);\n            nMax = effect('Bounce & Drop - ukramedia.com')(40);\n        }\n        $bm_rt = n = 0;\n        if (numKeys > 0) {\n            $bm_rt = n = nearestKey(time).index;\n            if (key(n).time > time)\n                n--;\n        }\n        if (n > 0) {\n            t = $bm_sub(time, key(n).time);\n            v = $bm_mul($bm_neg(velocityAtTime($bm_sub(key(n).time, 0.001))), e);\n            vl = length(v);\n            if ($bm_isInstanceOfArray(value)) {\n                vu = vl > 0 ? normalize(v) : [\n                    0,\n                    0,\n                    0\n                ];\n            } else {\n                vu = v < 0 ? -1 : 1;\n            }\n            tCur = 0;\n            segDur = $bm_div($bm_mul(2, vl), g);\n            tNext = segDur;\n            nb = 1;\n            while (tNext < t && nb <= nMax) {\n                vl *= e;\n                segDur *= e;\n                tCur = tNext;\n                tNext = $bm_sum(tNext, segDur);\n                nb++;\n            }\n            if (nb <= nMax) {\n                delta = $bm_sub(t, tCur);\n                $bm_rt = $bm_sum(value, $bm_mul($bm_mul(vu, delta), $bm_sub(vl, $bm_div($bm_mul(g, delta), 2))));\n            } else {\n                $bm_rt = value;\n            }\n        } else\n            $bm_rt = value;\n    } else {\n        $bm_rt = value;\n    }\n} catch (err) {\n    $bm_rt = value;\n}"},"sa":{"a":0,"k":0},"o":{"a":1,"k":[{"o":{"x":0.167,"y":0.167},"i":{"x":0.667,"y":1},"s":[50],"t":41.25},{"s":[0],"t":55}],"ix":11,"x":"var $bm_rt;\nvar opacityInertialBounce, opacityBounceBack, n, n, t, t, v, amp, freq, decay, v, amp, freq, decay, e, g, nMax, e, g, nMax, n, n, t, v, vl, vu, vu, tCur, segDur, tNext, nb, delta;\nopacityInertialBounce = effect('Bounce & Drop - ukramedia.com')(44);\nopacityBounceBack = effect('Bounce & Drop - ukramedia.com')(45);\ntry {\n    if (opacityInertialBounce == 1) {\n        $bm_rt = n = 0;\n        if (numKeys > 0) {\n            $bm_rt = n = nearestKey(time).index;\n            if (key(n).time > time) {\n                n--;\n            }\n        }\n        if (n == 0) {\n            $bm_rt = t = 0;\n        } else {\n            $bm_rt = t = $bm_sub(time, key(n).time);\n        }\n        if (effect('Bounce & Drop - ukramedia.com')(58) == 1) {\n            if (n > 0 && t < 1) {\n                v = velocityAtTime($bm_sub(key(n).time, $bm_div(thisComp.frameDuration, 10)));\n                amp = effect('Bounce & Drop - ukramedia.com')(59);\n                freq = effect('Bounce & Drop - ukramedia.com')(60);\n                decay = effect('Bounce & Drop - ukramedia.com')(61);\n                $bm_rt = $bm_sum(value, $bm_div($bm_mul($bm_mul(v, amp), Math.sin($bm_mul($bm_mul($bm_mul(freq, t), 2), Math.PI))), Math.exp($bm_mul(decay, t))));\n            } else {\n                $bm_rt = value;\n            }\n        } else {\n            if (n > 0 && t < 1) {\n                v = velocityAtTime($bm_sub(key(n).time, $bm_div(thisComp.frameDuration, 10)));\n                amp = effect('Bounce & Drop - ukramedia.com')(47);\n                freq = effect('Bounce & Drop - ukramedia.com')(48);\n                decay = effect('Bounce & Drop - ukramedia.com')(49);\n                $bm_rt = $bm_sum(value, $bm_div($bm_mul($bm_mul(v, amp), Math.sin($bm_mul($bm_mul($bm_mul(freq, t), 2), Math.PI))), Math.exp($bm_mul(decay, t))));\n            } else {\n                $bm_rt = value;\n            }\n        }\n    } else if (opacityBounceBack == 1) {\n        if (effect('Bounce & Drop - ukramedia.com')(64) == 1) {\n            e = effect('Bounce & Drop - ukramedia.com')(65);\n            g = effect('Bounce & Drop - ukramedia.com')(66);\n            nMax = effect('Bounce & Drop - ukramedia.com')(67);\n        } else {\n            e = effect('Bounce & Drop - ukramedia.com')(52);\n            g = effect('Bounce & Drop - ukramedia.com')(53);\n            nMax = effect('Bounce & Drop - ukramedia.com')(54);\n        }\n        $bm_rt = n = 0;\n        if (numKeys > 0) {\n            $bm_rt = n = nearestKey(time).index;\n            if (key(n).time > time)\n                n--;\n        }\n        if (n > 0) {\n            t = $bm_sub(time, key(n).time);\n            v = $bm_mul($bm_neg(velocityAtTime($bm_sub(key(n).time, 0.001))), e);\n            vl = length(v);\n            if ($bm_isInstanceOfArray(value)) {\n                vu = vl > 0 ? normalize(v) : [\n                    0,\n                    0,\n                    0\n                ];\n            } else {\n                vu = v < 0 ? -1 : 1;\n            }\n            tCur = 0;\n            segDur = $bm_div($bm_mul(2, vl), g);\n            tNext = segDur;\n            nb = 1;\n            while (tNext < t && nb <= nMax) {\n                vl *= e;\n                segDur *= e;\n                tCur = tNext;\n                tNext = $bm_sum(tNext, segDur);\n                nb++;\n            }\n            if (nb <= nMax) {\n                delta = $bm_sub(t, tCur);\n                $bm_rt = $bm_sum(value, $bm_mul($bm_mul(vu, delta), $bm_sub(vl, $bm_div($bm_mul(g, delta), 2))));\n            } else {\n                $bm_rt = value;\n            }\n        } else\n            $bm_rt = value;\n    } else {\n        $bm_rt = value;\n    }\n} catch (err) {\n    $bm_rt = value;\n}"}},"ef":[{"ty":5,"mn":"Pseudo/animationControl","nm":"Bounce & Drop - ukramedia.com","ix":1,"en":1,"ef":[{"ty":6,"mn":"Pseudo/animationControl-0001","nm":"Position","ix":1,"v":0},{"ty":7,"mn":"Pseudo/animationControl-0002","nm":"Enable Inertial Bounce","ix":2,"v":{"a":0,"k":0,"ix":2}},{"ty":7,"mn":"Pseudo/animationControl-0003","nm":"Enable Bounce Back","ix":3,"v":{"a":0,"k":0,"ix":3}},{"ty":6,"mn":"Pseudo/animationControl-0004","nm":"Inertial Bounce Options","ix":4,"v":0},{"ty":0,"mn":"Pseudo/animationControl-0005","nm":"Amplitude","ix":5,"v":{"a":0,"k":0.05,"ix":5}},{"ty":0,"mn":"Pseudo/animationControl-0006","nm":"Frequency","ix":6,"v":{"a":0,"k":4,"ix":6}},{"ty":0,"mn":"Pseudo/animationControl-0007","nm":"Decay","ix":7,"v":{"a":0,"k":8,"ix":7}},{"ty":6,"mn":"Pseudo/animationControl-0008","nm":"","ix":8,"v":0},{"ty":6,"mn":"Pseudo/animationControl-0009","nm":"Bounce Back Options","ix":9,"v":0},{"ty":0,"mn":"Pseudo/animationControl-0010","nm":"Elasticity","ix":10,"v":{"a":0,"k":0.7,"ix":10}},{"ty":0,"mn":"Pseudo/animationControl-0011","nm":"Gravity","ix":11,"v":{"a":0,"k":5000,"ix":11}},{"ty":0,"mn":"Pseudo/animationControl-0012","nm":"nMax","ix":12,"v":{"a":0,"k":9,"ix":12}},{"ty":6,"mn":"Pseudo/animationControl-0013","nm":"","ix":13,"v":0},{"ty":6,"mn":"Pseudo/animationControl-0014","nm":"","ix":14,"v":0},{"ty":6,"mn":"Pseudo/animationControl-0015","nm":"Scale","ix":15,"v":0},{"ty":7,"mn":"Pseudo/animationControl-0016","nm":"Enable Inertial Bounce","ix":16,"v":{"a":0,"k":1,"ix":16}},{"ty":7,"mn":"Pseudo/animationControl-0017","nm":"Enable Bounce Back","ix":17,"v":{"a":0,"k":0,"ix":17}},{"ty":6,"mn":"Pseudo/animationControl-0018","nm":"Inertial Bounce Options","ix":18,"v":0},{"ty":0,"mn":"Pseudo/animationControl-0019","nm":"Amplitude","ix":19,"v":{"a":0,"k":0.8,"ix":19}},{"ty":0,"mn":"Pseudo/animationControl-0020","nm":"Frequency","ix":20,"v":{"a":0,"k":4,"ix":20}},{"ty":0,"mn":"Pseudo/animationControl-0021","nm":"Decay","ix":21,"v":{"a":0,"k":8,"ix":21}},{"ty":6,"mn":"Pseudo/animationControl-0022","nm":"","ix":22,"v":0},{"ty":6,"mn":"Pseudo/animationControl-0023","nm":"Bounce Back Options","ix":23,"v":0},{"ty":0,"mn":"Pseudo/animationControl-0024","nm":"Elasticity","ix":24,"v":{"a":0,"k":0.7,"ix":24}},{"ty":0,"mn":"Pseudo/animationControl-0025","nm":"Gravity","ix":25,"v":{"a":0,"k":5000,"ix":25}},{"ty":0,"mn":"Pseudo/animationControl-0026","nm":"nMax","ix":26,"v":{"a":0,"k":9,"ix":26}},{"ty":6,"mn":"Pseudo/animationControl-0027","nm":"","ix":27,"v":0},{"ty":6,"mn":"Pseudo/animationControl-0028","nm":"","ix":28,"v":0},{"ty":6,"mn":"Pseudo/animationControl-0029","nm":"Rotation","ix":29,"v":0},{"ty":7,"mn":"Pseudo/animationControl-0030","nm":"Enable Inertial Bounce","ix":30,"v":{"a":0,"k":0,"ix":30}},{"ty":7,"mn":"Pseudo/animationControl-0031","nm":"Enable Bounce Back","ix":31,"v":{"a":0,"k":0,"ix":31}},{"ty":6,"mn":"Pseudo/animationControl-0032","nm":"Inertial Bounce Options","ix":32,"v":0},{"ty":0,"mn":"Pseudo/animationControl-0033","nm":"Amplitude","ix":33,"v":{"a":0,"k":0.05,"ix":33}},{"ty":0,"mn":"Pseudo/animationControl-0034","nm":"Frequency","ix":34,"v":{"a":0,"k":4,"ix":34}},{"ty":0,"mn":"Pseudo/animationControl-0035","nm":"Decay","ix":35,"v":{"a":0,"k":8,"ix":35}},{"ty":6,"mn":"Pseudo/animationControl-0036","nm":"","ix":36,"v":0},{"ty":6,"mn":"Pseudo/animationControl-0037","nm":"Bounce Back Options","ix":37,"v":0},{"ty":0,"mn":"Pseudo/animationControl-0038","nm":"Elasticity","ix":38,"v":{"a":0,"k":0.7,"ix":38}},{"ty":0,"mn":"Pseudo/animationControl-0039","nm":"Gravity","ix":39,"v":{"a":0,"k":5000,"ix":39}},{"ty":0,"mn":"Pseudo/animationControl-0040","nm":"nMax","ix":40,"v":{"a":0,"k":9,"ix":40}},{"ty":6,"mn":"Pseudo/animationControl-0041","nm":"","ix":41,"v":0},{"ty":6,"mn":"Pseudo/animationControl-0042","nm":"","ix":42,"v":0},{"ty":6,"mn":"Pseudo/animationControl-0043","nm":"Opacity","ix":43,"v":0},{"ty":7,"mn":"Pseudo/animationControl-0044","nm":"Enable Inertial Bounce","ix":44,"v":{"a":0,"k":0,"ix":44}},{"ty":7,"mn":"Pseudo/animationControl-0045","nm":"Enable Bounce Back","ix":45,"v":{"a":0,"k":0,"ix":45}},{"ty":6,"mn":"Pseudo/animationControl-0046","nm":"Inertial Bounce Options","ix":46,"v":0},{"ty":0,"mn":"Pseudo/animationControl-0047","nm":"Amplitude","ix":47,"v":{"a":0,"k":0.05,"ix":47}},{"ty":0,"mn":"Pseudo/animationControl-0048","nm":"Frequency","ix":48,"v":{"a":0,"k":4,"ix":48}},{"ty":0,"mn":"Pseudo/animationControl-0049","nm":"Decay","ix":49,"v":{"a":0,"k":8,"ix":49}},{"ty":6,"mn":"Pseudo/animationControl-0050","nm":"","ix":50,"v":0},{"ty":6,"mn":"Pseudo/animationControl-0051","nm":"Bounce Back Options","ix":51,"v":0},{"ty":0,"mn":"Pseudo/animationControl-0052","nm":"Elasticity","ix":52,"v":{"a":0,"k":0.7,"ix":52}},{"ty":0,"mn":"Pseudo/animationControl-0053","nm":"Gravity","ix":53,"v":{"a":0,"k":5000,"ix":53}},{"ty":0,"mn":"Pseudo/animationControl-0054","nm":"nMax","ix":54,"v":{"a":0,"k":9,"ix":54}},{"ty":6,"mn":"Pseudo/animationControl-0055","nm":"","ix":55,"v":0},{"ty":6,"mn":"Pseudo/animationControl-0056","nm":"","ix":56,"v":0},{"ty":6,"mn":"Pseudo/animationControl-0057","nm":"Global Inertial Bounce Options","ix":57,"v":0},{"ty":7,"mn":"Pseudo/animationControl-0058","nm":"Enable Global Inertial Bounce","ix":58,"v":{"a":0,"k":0,"ix":58}},{"ty":0,"mn":"Pseudo/animationControl-0059","nm":"Amplitude","ix":59,"v":{"a":0,"k":0.05,"ix":59}},{"ty":0,"mn":"Pseudo/animationControl-0060","nm":"Frequency","ix":60,"v":{"a":0,"k":4,"ix":60}},{"ty":0,"mn":"Pseudo/animationControl-0061","nm":"Decay","ix":61,"v":{"a":0,"k":8,"ix":61}},{"ty":6,"mn":"Pseudo/animationControl-0062","nm":"","ix":62,"v":0},{"ty":6,"mn":"Pseudo/animationControl-0063","nm":"Global Bounce Back Options","ix":63,"v":0},{"ty":7,"mn":"Pseudo/animationControl-0064","nm":"Enable Global Bounce Back","ix":64,"v":{"a":0,"k":0,"ix":64}},{"ty":0,"mn":"Pseudo/animationControl-0065","nm":"Elasticity","ix":65,"v":{"a":0,"k":0.7,"ix":65}},{"ty":0,"mn":"Pseudo/animationControl-0066","nm":"Gravity","ix":66,"v":{"a":0,"k":5000,"ix":66}},{"ty":0,"mn":"Pseudo/animationControl-0067","nm":"nMax","ix":67,"v":{"a":0,"k":9,"ix":67}},{"ty":6,"mn":"Pseudo/animationControl-0068","nm":"","ix":68,"v":0}]}],"shapes":[{"ty":"gr","bm":0,"hd":false,"mn":"ADBE Vector Group","nm":"Group 1","ix":1,"cix":2,"np":2,"it":[{"ty":"sh","bm":0,"hd":false,"mn":"ADBE Vector Shape - Group","nm":"Path 1","ix":1,"d":1,"ks":{"a":0,"k":{"c":true,"i":[[0,-77.215],[77.216,0],[0,77.215],[-77.215,0]],"o":[[0,77.215],[-77.215,0],[0,-77.215],[77.216,0]],"v":[[139.811,0],[0,139.811],[-139.811,0],[0,-139.811]]},"ix":2}},{"ty":"fl","bm":0,"hd":false,"mn":"ADBE Vector Graphic - Fill","nm":"Fill 1","c":{"a":0,"k":[0.1725,0.2784,0.4431],"ix":4},"r":1,"o":{"a":0,"k":100,"ix":5}},{"ty":"tr","a":{"a":0,"k":[0,0],"ix":1},"s":{"a":0,"k":[100,100],"ix":3},"sk":{"a":0,"k":0,"ix":4},"p":{"a":0,"k":[140.061,140.061],"ix":2},"r":{"a":0,"k":0,"ix":6},"sa":{"a":0,"k":0,"ix":5},"o":{"a":0,"k":100,"ix":7}}]}],"ind":4}],"v":"5.7.11","fr":30,"op":60,"ip":0,"assets":[]}